carte_blanche/__init__.py
carte_blanche/api/__init__.py
carte_blanche/api/authentication.py
carte_blanche/api/base_route.py
carte_blanche/db/__init__.py
carte_blanche/db/mongodb.py
carte_blanche/db/psql.py
carte_blanche/find_path/__init__.py
carte_blanche/find_path/find_path.py
carte_blanche/lodash/__init__.py
carte_blanche/lodash/chunk.py
carte_blanche/logger/__init__.py
carte_blanche/logger/logger.py
carte_blanche/redis_util/__init__.py
carte_blanche/redis_util/redis_util.py
carte_blanche/serializers/__errors__.py
carte_blanche/serializers/__init__.py
carte_blanche/serializers/md5_.py
carte_blanche/serializers/salt.py
carte_blanche/serializers/sha_.py
carte_blanche/validators/__errors__.py
carte_blanche/validators/__init__.py
carte_blanche/validators/validator.py
carte_blanche-1.3.8.dist-info/METADATA
carte_blanche-1.3.8.dist-info/WHEEL
carte_blanche-1.3.8.dist-info/top_level.txt
carte_blanche-1.3.8.dist-info/RECORD
