Metadata-Version: 2.1
Name: carte-blanche
Version: 1.3.8
Summary: A package of web server development libraries
Home-page: https://github.com/huffmsa/carte-blanche-python-utils
Author: Sam Huffman
Author-email: huffmsa@gmail.com
License: MIT
Platform: UNKNOWN
Requires-Dist: astroid (==2.5)
Requires-Dist: atomicwrites (==1.4.0)
Requires-Dist: attrs (==21.2.0)
Requires-Dist: cffi (==1.14.6)
Requires-Dist: coloredlogs (==15.0.1)
Requires-Dist: cryptography (==3.4.7)
Requires-Dist: entrypoints (==0.3)
Requires-Dist: falcon (==2.0.0)
Requires-Dist: flake8 (==3.7.9)
Requires-Dist: humanfriendly (==9.2)
Requires-Dist: isort (==4.3.21)
Requires-Dist: jeepney (==0.7.1)
Requires-Dist: jsonschema (==2.6.0)
Requires-Dist: lazy-object-proxy (==1.4.3)
Requires-Dist: mccabe (==0.6.1)
Requires-Dist: more-itertools (==4.3.0)
Requires-Dist: pip-autoremove (==0.9.1)
Requires-Dist: pluggy (==0.7.1)
Requires-Dist: psycopg2-binary (==2.9.1)
Requires-Dist: py (==1.10.0)
Requires-Dist: pycodestyle (==2.5.0)
Requires-Dist: pycparser (==2.20)
Requires-Dist: pyflakes (==2.1.1)
Requires-Dist: pylint (==2.5.3)
Requires-Dist: pymongo (==3.10.1)
Requires-Dist: pytest (==3.7.2)
Requires-Dist: redis (==3.4.1)
Requires-Dist: SecretStorage (==3.3.1)
Requires-Dist: six (==1.14.0)
Requires-Dist: SQLAlchemy (==1.3.15)
Requires-Dist: toml (==0.10.1)
Requires-Dist: wrapt (==1.11.2)
